shelter/__init__.py
shelter/shelter.py
shelter/helpers/__init__.py
shelter/helpers/cli.py
shelter/helpers/ip_port_handler.py
shelter/helpers/shell_handler.py
shelter/helpers/stylize.py
shelter/modules/__init__.py
shelter/modules/shell_copy.py
shelter/modules/web.py
pwnshelter-2.0.1.dist-info/LICENSE
pwnshelter-2.0.1.dist-info/METADATA
pwnshelter-2.0.1.dist-info/WHEEL
pwnshelter-2.0.1.dist-info/entry_points.txt
pwnshelter-2.0.1.dist-info/top_level.txt
pwnshelter-2.0.1.dist-info/RECORD
