Metadata-Version: 2.1
Name: pwnshelter
Version: 2.0.1
Summary: Reverse Shell Payload Handler
Home-page: https://github.com/Xyan1d3/shelter
Author: Bides 'Xyan1d3' Das
Author-email: blackviking.soapmactavish@gmail.com
License: UNKNOWN
Project-URL: Bug Tracker, https://github.com/Xyan1d3/shelter/issues
Platform: UNKNOWN
Classifier: Programming Language :: Python :: 3
Classifier: License :: OSI Approved :: Apache Software License
Classifier: Operating System :: POSIX :: Linux
Requires-Python: >=3.6
Requires-Dist: argparse (>=1.2)
Requires-Dist: pyperclip (>=1.6.0)
Requires-Dist: netifaces (>=0.10.8)
Requires-Dist: requests (>=2.25.1)
